pyjanssen/__init__.py
pyjanssen/janssen_mcm.py
pyjanssen/response.py
pyjanssen-0.1.2.dist-info/LICENSE
pyjanssen-0.1.2.dist-info/METADATA
pyjanssen-0.1.2.dist-info/WHEEL
pyjanssen-0.1.2.dist-info/top_level.txt
pyjanssen-0.1.2.dist-info/RECORD
