Metadata-Version: 2.1
Name: pyjanssen
Version: 0.1.2
Summary: Wrapper for cacli.exe for Janssen Precision Engineering MCM module
Home-page: https://github.com/Laukei/pyjanssen
Author: Robert Heath
Author-email: rob@robheath.me.uk
License: UNKNOWN
Platform: UNKNOWN
Classifier: Programming Language :: Python :: 3
Classifier: License :: OSI Approved :: MIT License
Classifier: Operating System :: Microsoft :: Windows
Classifier: Development Status :: 3 - Alpha
